xcloud_client/__init__.py
xcloud_client/xCloud_client.py
xcloud_client-3.4.dist-info/METADATA
xcloud_client-3.4.dist-info/WHEEL
xcloud_client-3.4.dist-info/top_level.txt
xcloud_client-3.4.dist-info/RECORD
