Metadata-Version: 2.1
Name: xcloud-client
Version: 3.4
Summary: UNKNOWN
License: UNKNOWN
Platform: UNKNOWN
Requires-Dist: JayDeBeApi (==1.2.3)
